[
  {
    "id": "V9vuCByb6js",
    "title": "Sabrina Carpenter - Tears (Official Video)",
    "channel": "SabrinaCarpenterVEVO",
    "views": 25055523,
    "views_str": "25.1M views",
    "url": "https://www.youtube.com/watch?v=V9vuCByb6js",
    "embed_url": "https://www.youtube.com/embed/V9vuCByb6js",
    "thumbnail": "https://i.ytimg.com/vi/V9vuCByb6js/mqdefault.jpg",
    "published_at": "2025-08-29T04:00:07Z",
    "published_date_formatted": "29.08.2025",
    "viewChange": 25055523,
    "viewChange_str": "+25,055,523",
    "trend": "up",
    "rank": 1,
    "rankChange": 18,
    "rankChange_str": "+18"
  },
  {
    "id": "HnYtDIW7elY",
    "title": "ZEROBASEONE (제로베이스원) 'ICONIK' MV",
    "channel": "ZEROBASEONE",
    "views": 9682375,
    "views_str": "9.7M views",
    "url": "https://www.youtube.com/watch?v=HnYtDIW7elY",
    "embed_url": "https://www.youtube.com/embed/HnYtDIW7elY",
    "thumbnail": "https://i.ytimg.com/vi/HnYtDIW7elY/mqdefault.jpg",
    "published_at": "2025-09-01T09:00:03Z",
    "published_date_formatted": "01.09.2025",
    "viewChange": 9682375,
    "viewChange_str": "+9,682,375",
    "trend": "up",
    "rank": 2,
    "rankChange": 46,
    "rankChange_str": "+46"
  },
  {
    "id": "RYI-WG_HFV8",
    "title": "JUJUTSU KAISEN The Culling Game | Official Teaser | Crunchyroll",
    "channel": "Crunchyroll",
    "views": 5457614,
    "views_str": "5.5M views",
    "url": "https://www.youtube.com/watch?v=RYI-WG_HFV8",
    "embed_url": "https://www.youtube.com/embed/RYI-WG_HFV8",
    "thumbnail": "https://i.ytimg.com/vi/RYI-WG_HFV8/mqdefault.jpg",
    "published_at": "2025-08-31T15:00:45Z",
    "published_date_formatted": "31.08.2025",
    "viewChange": 5457614,
    "viewChange_str": "+5,457,614",
    "trend": "up",
    "rank": 3,
    "rankChange": -1,
    "rankChange_str": "-1"
  },
  {
    "id": "JIRqdeNl2cU",
    "title": "Race Highlights | 2025 Dutch Grand Prix",
    "channel": "FORMULA 1",
    "views": 5340433,
    "views_str": "5.3M views",
    "url": "https://www.youtube.com/watch?v=JIRqdeNl2cU",
    "embed_url": "https://www.youtube.com/embed/JIRqdeNl2cU",
    "thumbnail": "https://i.ytimg.com/vi/JIRqdeNl2cU/mqdefault.jpg",
    "published_at": "2025-08-31T15:54:30Z",
    "published_date_formatted": "31.08.2025",
    "viewChange": 5340433,
    "viewChange_str": "+5,340,433",
    "trend": "up",
    "rank": 4,
    "rankChange": 8,
    "rankChange_str": "+8"
  },
  {
    "id": "G4Df2vAnKZo",
    "title": "KNIGHTS OF GUINEVERE [TRAILER]",
    "channel": "GLITCH",
    "views": 3419975,
    "views_str": "3.4M views",
    "url": "https://www.youtube.com/watch?v=G4Df2vAnKZo",
    "embed_url": "https://www.youtube.com/embed/G4Df2vAnKZo",
    "thumbnail": "https://i.ytimg.com/vi/G4Df2vAnKZo/mqdefault.jpg",
    "published_at": "2025-08-29T19:00:15Z",
    "published_date_formatted": "29.08.2025",
    "viewChange": 3419975,
    "viewChange_str": "+3,419,975",
    "trend": "up",
    "rank": 5,
    "rankChange": 12,
    "rankChange_str": "+12"
  },
  {
    "id": "Vd09-_G_tD0",
    "title": "99 Nights - The Deer (official song)",
    "channel": "Horror Skunx",
    "views": 3377415,
    "views_str": "3.4M views",
    "url": "https://www.youtube.com/watch?v=Vd09-_G_tD0",
    "embed_url": "https://www.youtube.com/embed/Vd09-_G_tD0",
    "thumbnail": "https://i.ytimg.com/vi/Vd09-_G_tD0/mqdefault.jpg",
    "published_at": "2025-08-29T20:15:02Z",
    "published_date_formatted": "29.08.2025",
    "viewChange": 3377415,
    "viewChange_str": "+3,377,415",
    "trend": "up",
    "rank": 6,
    "rankChange": 32,
    "rankChange_str": "+32"
  },
  {
    "id": "3jQE-v5IZdU",
    "title": "Nobody Puts Baby Dragon in a Locker! ft. bbno$ (Official EVO Trailer)",
    "channel": "Clash Royale",
    "views": 3311000,
    "views_str": "3.3M views",
    "url": "https://www.youtube.com/watch?v=3jQE-v5IZdU",
    "embed_url": "https://www.youtube.com/embed/3jQE-v5IZdU",
    "thumbnail": "https://i.ytimg.com/vi/3jQE-v5IZdU/mqdefault.jpg",
    "published_at": "2025-08-30T15:00:10Z",
    "published_date_formatted": "30.08.2025",
    "viewChange": 3311000,
    "viewChange_str": "+3,311,000",
    "trend": "up",
    "rank": 7,
    "rankChange": 36,
    "rankChange_str": "+36"
  },
  {
    "id": "qS7OsvKqojg",
    "title": "Stray Kids \"삐처리 (BLEEP)\" Video",
    "channel": "Stray Kids",
    "views": 2647376,
    "views_str": "2.6M views",
    "url": "https://www.youtube.com/watch?v=qS7OsvKqojg",
    "embed_url": "https://www.youtube.com/embed/qS7OsvKqojg",
    "thumbnail": "https://i.ytimg.com/vi/qS7OsvKqojg/mqdefault.jpg",
    "published_at": "2025-08-31T14:00:02Z",
    "published_date_formatted": "31.08.2025",
    "viewChange": 2647376,
    "viewChange_str": "+2,647,376",
    "trend": "up",
    "rank": 8,
    "rankChange": 5,
    "rankChange_str": "+5"
  },
  {
    "id": "UFPT7_U4oyc",
    "title": "The Summer I Turned Pretty Season 3 - Official Final Trailer | Prime Video",
    "channel": "Prime Video",
    "views": 2356588,
    "views_str": "2.4M views",
    "url": "https://www.youtube.com/watch?v=UFPT7_U4oyc",
    "embed_url": "https://www.youtube.com/embed/UFPT7_U4oyc",
    "thumbnail": "https://i.ytimg.com/vi/UFPT7_U4oyc/mqdefault.jpg",
    "published_at": "2025-08-29T14:59:53Z",
    "published_date_formatted": "29.08.2025",
    "viewChange": 2356588,
    "viewChange_str": "+2,356,588",
    "trend": "up",
    "rank": 9,
    "rankChange": 11,
    "rankChange_str": "+11"
  },
  {
    "id": "TU0AxQ2of7I",
    "title": "Sergio Ramos - CIBELES (Official Video)",
    "channel": "Sergio Ramos",
    "views": 1553484,
    "views_str": "1.6M views",
    "url": "https://www.youtube.com/watch?v=TU0AxQ2of7I",
    "embed_url": "https://www.youtube.com/embed/TU0AxQ2of7I",
    "thumbnail": "https://i.ytimg.com/vi/TU0AxQ2of7I/mqdefault.jpg",
    "published_at": "2025-08-31T17:00:08Z",
    "published_date_formatted": "31.08.2025",
    "viewChange": 1553484,
    "viewChange_str": "+1,553,484",
    "trend": "up",
    "rank": 10,
    "rankChange": -9,
    "rankChange_str": "-9"
  },
  {
    "id": "wnUQ2cqd_Y8",
    "title": "ROBÉ EL NUEVO BRAINROT OG DEL EVENTO SECRETO COMPLETO (STEAL A BRAINROT ROBLOX)",
    "channel": "Chuy Mine",
    "views": 1169337,
    "views_str": "1.2M views",
    "url": "https://www.youtube.com/watch?v=wnUQ2cqd_Y8",
    "embed_url": "https://www.youtube.com/embed/wnUQ2cqd_Y8",
    "thumbnail": "https://i.ytimg.com/vi/wnUQ2cqd_Y8/mqdefault.jpg",
    "published_at": "2025-08-31T21:15:02Z",
    "published_date_formatted": "31.08.2025",
    "viewChange": 1169337,
    "viewChange_str": "+1,169,337",
    "trend": "up",
    "rank": 11,
    "rankChange": 38,
    "rankChange_str": "+38"
  },
  {
    "id": "F4l4n7zgfCA",
    "title": "Yapi - DONDE TE ESCONDES? 2.0 ft JC Reyes (Video Oficial)",
    "channel": "Yapi",
    "views": 1164817,
    "views_str": "1.2M views",
    "url": "https://www.youtube.com/watch?v=F4l4n7zgfCA",
    "embed_url": "https://www.youtube.com/embed/F4l4n7zgfCA",
    "thumbnail": "https://i.ytimg.com/vi/F4l4n7zgfCA/mqdefault.jpg",
    "published_at": "2025-08-27T22:00:06Z",
    "published_date_formatted": "27.08.2025",
    "viewChange": 1164817,
    "viewChange_str": "+1,164,817",
    "trend": "up",
    "rank": 12,
    "rankChange": -8,
    "rankChange_str": "-8"
  },
  {
    "id": "mPBlzDS0cUg",
    "title": "COMO OREO 💖 |  BLESSD ❌ FUERZA REGIDA ❌ OVY ON THE DRUMS",
    "channel": "BLESSD EL BENDITO 💙",
    "views": 1050691,
    "views_str": "1.1M views",
    "url": "https://www.youtube.com/watch?v=mPBlzDS0cUg",
    "embed_url": "https://www.youtube.com/embed/mPBlzDS0cUg",
    "thumbnail": "https://i.ytimg.com/vi/mPBlzDS0cUg/mqdefault.jpg",
    "published_at": "2025-08-30T00:00:06Z",
    "published_date_formatted": "30.08.2025",
    "viewChange": 1050691,
    "viewChange_str": "+1,050,691",
    "trend": "up",
    "rank": 13,
    "rankChange": 33,
    "rankChange_str": "+33"
  },
  {
    "id": "NlHD4ndO-z0",
    "title": "Welcome to LIL FANTASY CHAEYOUNG “AVOCADO(feat.Gliiico)”",
    "channel": "JYP Entertainment",
    "views": 922824,
    "views_str": "922.8K views",
    "url": "https://www.youtube.com/watch?v=NlHD4ndO-z0",
    "embed_url": "https://www.youtube.com/embed/NlHD4ndO-z0",
    "thumbnail": "https://i.ytimg.com/vi/NlHD4ndO-z0/mqdefault.jpg",
    "published_at": "2025-08-31T15:00:04Z",
    "published_date_formatted": "31.08.2025",
    "viewChange": 922824,
    "viewChange_str": "+922,824",
    "trend": "up",
    "rank": 14,
    "rankChange": 36,
    "rankChange_str": "+36"
  },
  {
    "id": "gjIi6eqxeTo",
    "title": "Keane - Somewhere Only We Know (Lyrics)",
    "channel": "Unique Rock",
    "views": 731150,
    "views_str": "731.1K views",
    "url": "https://www.youtube.com/watch?v=gjIi6eqxeTo",
    "embed_url": "https://www.youtube.com/embed/gjIi6eqxeTo",
    "thumbnail": "https://i.ytimg.com/vi/gjIi6eqxeTo/mqdefault.jpg",
    "published_at": "2025-08-30T11:30:38Z",
    "published_date_formatted": "30.08.2025",
    "viewChange": 731150,
    "viewChange_str": "+731,150",
    "trend": "up",
    "rank": 15,
    "rankChange": 1,
    "rankChange_str": "+1"
  },
  {
    "id": "Ohl2rN9ED_U",
    "title": "MEJORÉ los COFRES en 99 noches",
    "channel": "LeoXter",
    "views": 730011,
    "views_str": "730.0K views",
    "url": "https://www.youtube.com/watch?v=Ohl2rN9ED_U",
    "embed_url": "https://www.youtube.com/embed/Ohl2rN9ED_U",
    "thumbnail": "https://i.ytimg.com/vi/Ohl2rN9ED_U/mqdefault.jpg",
    "published_at": "2025-09-01T15:46:02Z",
    "published_date_formatted": "01.09.2025",
    "viewChange": 730011,
    "viewChange_str": "+730,011",
    "trend": "up",
    "rank": 16,
    "rankChange": 19,
    "rankChange_str": "+19"
  },
  {
    "id": "JSwk05Yhess",
    "title": "RUN OR BRAWL! - Subway Surfers X Brawl Stars Animation Trailer",
    "channel": "Brawl Stars",
    "views": 681001,
    "views_str": "681.0K views",
    "url": "https://www.youtube.com/watch?v=JSwk05Yhess",
    "embed_url": "https://www.youtube.com/embed/JSwk05Yhess",
    "thumbnail": "https://i.ytimg.com/vi/JSwk05Yhess/mqdefault.jpg",
    "published_at": "2025-09-02T09:18:19Z",
    "published_date_formatted": "02.09.2025",
    "viewChange": 681001,
    "viewChange_str": "+681,001",
    "trend": "up",
    "rank": 17,
    "rankChange": -8,
    "rankChange_str": "-8"
  },
  {
    "id": "6Qxk2H2E8hA",
    "title": "ABRÍ UN PARQUE ACUATICO | Waterpark Simulator",
    "channel": "Rubius Z",
    "views": 657199,
    "views_str": "657.2K views",
    "url": "https://www.youtube.com/watch?v=6Qxk2H2E8hA",
    "embed_url": "https://www.youtube.com/embed/6Qxk2H2E8hA",
    "thumbnail": "https://i.ytimg.com/vi/6Qxk2H2E8hA/mqdefault.jpg",
    "published_at": "2025-09-01T18:55:27Z",
    "published_date_formatted": "01.09.2025",
    "viewChange": 657199,
    "viewChange_str": "+657,199",
    "trend": "up",
    "rank": 18,
    "rankChange": -15,
    "rankChange_str": "-15"
  },
  {
    "id": "MX7suzOTmhA",
    "title": "L7OR - SRA LI SRA (Official Music Video) | الحر - صرا لي صرا",
    "channel": "L7OR - الحر",
    "views": 636111,
    "views_str": "636.1K views",
    "url": "https://www.youtube.com/watch?v=MX7suzOTmhA",
    "embed_url": "https://www.youtube.com/embed/MX7suzOTmhA",
    "thumbnail": "https://i.ytimg.com/vi/MX7suzOTmhA/mqdefault.jpg",
    "published_at": "2025-08-31T20:07:23Z",
    "published_date_formatted": "31.08.2025",
    "viewChange": 636111,
    "viewChange_str": "+636,111",
    "trend": "up",
    "rank": 19,
    "rankChange": 9,
    "rankChange_str": "+9"
  },
  {
    "id": "ri0Qual6WY4",
    "title": "Hice un ESCÁNER para Descubrir los SECRETOS de Mis Amigos en Minecraft!",
    "channel": "Dagar",
    "views": 583465,
    "views_str": "583.5K views",
    "url": "https://www.youtube.com/watch?v=ri0Qual6WY4",
    "embed_url": "https://www.youtube.com/embed/ri0Qual6WY4",
    "thumbnail": "https://i.ytimg.com/vi/ri0Qual6WY4/mqdefault.jpg",
    "published_at": "2025-09-01T18:00:33Z",
    "published_date_formatted": "01.09.2025",
    "viewChange": 583465,
    "viewChange_str": "+583,465",
    "trend": "up",
    "rank": 20,
    "rankChange": 27,
    "rankChange_str": "+27"
  },
  {
    "id": "HRCIw6qnQbg",
    "title": "Eladio Carrión - Sauce Boy Freestyle 6 (Video Oficial)",
    "channel": "Eladio Carrion",
    "views": 542816,
    "views_str": "542.8K views",
    "url": "https://www.youtube.com/watch?v=HRCIw6qnQbg",
    "embed_url": "https://www.youtube.com/embed/HRCIw6qnQbg",
    "thumbnail": "https://i.ytimg.com/vi/HRCIw6qnQbg/mqdefault.jpg",
    "published_at": "2025-08-30T16:00:04Z",
    "published_date_formatted": "30.08.2025",
    "viewChange": 542816,
    "viewChange_str": "+542,816",
    "trend": "up",
    "rank": 21,
    "rankChange": 15,
    "rankChange_str": "+15"
  },
  {
    "id": "Vhvj28mAwi8",
    "title": "MAXEO LA NUEVA CARTA Y ESTA ROTISISIMA!! - BENIJU",
    "channel": "BENIJU",
    "views": 477543,
    "views_str": "477.5K views",
    "url": "https://www.youtube.com/watch?v=Vhvj28mAwi8",
    "embed_url": "https://www.youtube.com/embed/Vhvj28mAwi8",
    "thumbnail": "https://i.ytimg.com/vi/Vhvj28mAwi8/mqdefault.jpg",
    "published_at": "2025-09-01T18:15:02Z",
    "published_date_formatted": "01.09.2025",
    "viewChange": 477543,
    "viewChange_str": "+477,543",
    "trend": "up",
    "rank": 22,
    "rankChange": -7,
    "rankChange_str": "-7"
  },
  {
    "id": "guIbAF0F9pI",
    "title": "el fin de Roblox.",
    "channel": "RickyEdit",
    "views": 459162,
    "views_str": "459.2K views",
    "url": "https://www.youtube.com/watch?v=guIbAF0F9pI",
    "embed_url": "https://www.youtube.com/embed/guIbAF0F9pI",
    "thumbnail": "https://i.ytimg.com/vi/guIbAF0F9pI/mqdefault.jpg",
    "published_at": "2025-08-30T13:01:20Z",
    "published_date_formatted": "30.08.2025",
    "viewChange": 459162,
    "viewChange_str": "+459,162",
    "trend": "up",
    "rank": 23,
    "rankChange": 8,
    "rankChange_str": "+8"
  },
  {
    "id": "GpsVMJkppuY",
    "title": "Beéle, Westcol, Ovy On The Drums - LA PLENA (W Sound 05) [Letra/Lyrics]",
    "channel": "LatinVerse",
    "views": 438854,
    "views_str": "438.9K views",
    "url": "https://www.youtube.com/watch?v=GpsVMJkppuY",
    "embed_url": "https://www.youtube.com/embed/GpsVMJkppuY",
    "thumbnail": "https://i.ytimg.com/vi/GpsVMJkppuY/mqdefault.jpg",
    "published_at": "2025-08-27T11:30:12Z",
    "published_date_formatted": "27.08.2025",
    "viewChange": 438854,
    "viewChange_str": "+438,854",
    "trend": "up",
    "rank": 24,
    "rankChange": -2,
    "rankChange_str": "-2"
  },
  {
    "id": "2mH396WCN0U",
    "title": "House of Guinness | Official Trailer | Netflix",
    "channel": "Netflix",
    "views": 427091,
    "views_str": "427.1K views",
    "url": "https://www.youtube.com/watch?v=2mH396WCN0U",
    "embed_url": "https://www.youtube.com/embed/2mH396WCN0U",
    "thumbnail": "https://i.ytimg.com/vi/2mH396WCN0U/mqdefault.jpg",
    "published_at": "2025-09-01T15:00:00Z",
    "published_date_formatted": "01.09.2025",
    "viewChange": 427091,
    "viewChange_str": "+427,091",
    "trend": "up",
    "rank": 25,
    "rankChange": -11,
    "rankChange_str": "-11"
  },
  {
    "id": "BiRZM8SnucE",
    "title": "Beéle - si te pillara (Letra)",
    "channel": "The Best Flow",
    "views": 416215,
    "views_str": "416.2K views",
    "url": "https://www.youtube.com/watch?v=BiRZM8SnucE",
    "embed_url": "https://www.youtube.com/embed/BiRZM8SnucE",
    "thumbnail": "https://i.ytimg.com/vi/BiRZM8SnucE/mqdefault.jpg",
    "published_at": "2025-08-29T14:00:06Z",
    "published_date_formatted": "29.08.2025",
    "viewChange": 416215,
    "viewChange_str": "+416,215",
    "trend": "up",
    "rank": 26,
    "rankChange": -16,
    "rankChange_str": "-16"
  },
  {
    "id": "ZShhNIMeEYc",
    "title": "Te recomiendo 100 videojuegos",
    "channel": "alexelcapo",
    "views": 287755,
    "views_str": "287.8K views",
    "url": "https://www.youtube.com/watch?v=ZShhNIMeEYc",
    "embed_url": "https://www.youtube.com/embed/ZShhNIMeEYc",
    "thumbnail": "https://i.ytimg.com/vi/ZShhNIMeEYc/mqdefault.jpg",
    "published_at": "2025-08-30T18:47:42Z",
    "published_date_formatted": "30.08.2025",
    "viewChange": 287755,
    "viewChange_str": "+287,755",
    "trend": "up",
    "rank": 27,
    "rankChange": 12,
    "rankChange_str": "+12"
  },
  {
    "id": "e9dFZJaZAZs",
    "title": "Ubers x Bastard Munchen (Blue Lock) | Liga Neo Egoísta Rap #3 | Kballero",
    "channel": "Kballero Rap",
    "views": 278039,
    "views_str": "278.0K views",
    "url": "https://www.youtube.com/watch?v=e9dFZJaZAZs",
    "embed_url": "https://www.youtube.com/embed/e9dFZJaZAZs",
    "thumbnail": "https://i.ytimg.com/vi/e9dFZJaZAZs/mqdefault.jpg",
    "published_at": "2025-08-30T18:45:06Z",
    "published_date_formatted": "30.08.2025",
    "viewChange": 278039,
    "viewChange_str": "+278,039",
    "trend": "up",
    "rank": 28,
    "rankChange": 14,
    "rankChange_str": "+14"
  },
  {
    "id": "oE2qF1AB-ks",
    "title": "[Official Trailer] That Summer ผมเจอเจ้าชายบนชายหาด",
    "channel": "GMMTV OFFICIAL​​",
    "views": 277612,
    "views_str": "277.6K views",
    "url": "https://www.youtube.com/watch?v=oE2qF1AB-ks",
    "embed_url": "https://www.youtube.com/embed/oE2qF1AB-ks",
    "thumbnail": "https://i.ytimg.com/vi/oE2qF1AB-ks/mqdefault.jpg",
    "published_at": "2025-09-01T11:01:25Z",
    "published_date_formatted": "01.09.2025",
    "viewChange": 277612,
    "viewChange_str": "+277,612",
    "trend": "up",
    "rank": 29,
    "rankChange": -3,
    "rankChange_str": "-3"
  },
  {
    "id": "-tyoFt26YWI",
    "title": "EL REMAKE QUE MÁS HE ESPERADO ❗ - Metal Gear Solid Delta: Snake Eater #1",
    "channel": "IlloJuan",
    "views": 271877,
    "views_str": "271.9K views",
    "url": "https://www.youtube.com/watch?v=-tyoFt26YWI",
    "embed_url": "https://www.youtube.com/embed/-tyoFt26YWI",
    "thumbnail": "https://i.ytimg.com/vi/-tyoFt26YWI/mqdefault.jpg",
    "published_at": "2025-09-01T13:15:01Z",
    "published_date_formatted": "01.09.2025",
    "viewChange": 271877,
    "viewChange_str": "+271,877",
    "trend": "up",
    "rank": 30,
    "rankChange": -24,
    "rankChange_str": "-24"
  },
  {
    "id": "sKN5TvnriSY",
    "title": "Blessd, Anuel AA, Kris R, Luar La L - YOGURCITO REMIX Ft. ROA, Yan Block (LETRA)",
    "channel": "RadioReggaeton",
    "views": 258788,
    "views_str": "258.8K views",
    "url": "https://www.youtube.com/watch?v=sKN5TvnriSY",
    "embed_url": "https://www.youtube.com/embed/sKN5TvnriSY",
    "thumbnail": "https://i.ytimg.com/vi/sKN5TvnriSY/mqdefault.jpg",
    "published_at": "2025-08-30T18:45:04Z",
    "published_date_formatted": "30.08.2025",
    "viewChange": 258788,
    "viewChange_str": "+258,788",
    "trend": "up",
    "rank": 31,
    "rankChange": -1,
    "rankChange_str": "-1"
  },
  {
    "id": "QmHjKLyKgjI",
    "title": "Vicente Fernández - Un Millón de Primaveras (Letra)",
    "channel": "warui.",
    "views": 253405,
    "views_str": "253.4K views",
    "url": "https://www.youtube.com/watch?v=QmHjKLyKgjI",
    "embed_url": "https://www.youtube.com/embed/QmHjKLyKgjI",
    "thumbnail": "https://i.ytimg.com/vi/QmHjKLyKgjI/mqdefault.jpg",
    "published_at": "2025-08-31T21:30:04Z",
    "published_date_formatted": "31.08.2025",
    "viewChange": 253405,
    "viewChange_str": "+253,405",
    "trend": "up",
    "rank": 32,
    "rankChange": 0,
    "rankChange_str": "+0"
  },
  {
    "id": "6eacLzK4SF4",
    "title": "🔴 -LATORTUGA DESTARTALADA ABRE SUS PUERTAS - MARBELLA  3",
    "channel": "Nexxuz World",
    "views": 223515,
    "views_str": "223.5K views",
    "url": "https://www.youtube.com/watch?v=6eacLzK4SF4",
    "embed_url": "https://www.youtube.com/embed/6eacLzK4SF4",
    "thumbnail": "https://i.ytimg.com/vi/6eacLzK4SF4/mqdefault.jpg",
    "published_at": "2025-09-02T01:08:04Z",
    "published_date_formatted": "02.09.2025",
    "viewChange": 223515,
    "viewChange_str": "+223,515",
    "trend": "up",
    "rank": 33,
    "rankChange": -15,
    "rankChange_str": "-15"
  },
  {
    "id": "8QrR6GbtoBU",
    "title": "Los SUPER TOBOGANES crean ACCIDENTES 🌊 #4",
    "channel": "UVESITOO",
    "views": 195647,
    "views_str": "195.6K views",
    "url": "https://www.youtube.com/watch?v=8QrR6GbtoBU",
    "embed_url": "https://www.youtube.com/embed/8QrR6GbtoBU",
    "thumbnail": "https://i.ytimg.com/vi/8QrR6GbtoBU/mqdefault.jpg",
    "published_at": "2025-08-31T18:35:22Z",
    "published_date_formatted": "31.08.2025",
    "viewChange": 195647,
    "viewChange_str": "+195,647",
    "trend": "up",
    "rank": 34,
    "rankChange": -10,
    "rankChange_str": "-10"
  },
  {
    "id": "krTX7A3VnQc",
    "title": "¡Vencí a Steal a Brainrot en 30 Dias!",
    "channel": "CREATIVE Juega!",
    "views": 182089,
    "views_str": "182.1K views",
    "url": "https://www.youtube.com/watch?v=krTX7A3VnQc",
    "embed_url": "https://www.youtube.com/embed/krTX7A3VnQc",
    "thumbnail": "https://i.ytimg.com/vi/krTX7A3VnQc/mqdefault.jpg",
    "published_at": "2025-09-01T19:00:44Z",
    "published_date_formatted": "01.09.2025",
    "viewChange": 182089,
    "viewChange_str": "+182,089",
    "trend": "up",
    "rank": 35,
    "rankChange": -8,
    "rankChange_str": "-8"
  },
  {
    "id": "Ulzih91lY44",
    "title": "Bryant Myers, Dei V, SAIKO - Duro Ma (Video Oficial) | Millo Gangster Club",
    "channel": "Bryant Myers",
    "views": 181466,
    "views_str": "181.5K views",
    "url": "https://www.youtube.com/watch?v=Ulzih91lY44",
    "embed_url": "https://www.youtube.com/embed/Ulzih91lY44",
    "thumbnail": "https://i.ytimg.com/vi/Ulzih91lY44/mqdefault.jpg",
    "published_at": "2025-08-30T19:00:06Z",
    "published_date_formatted": "30.08.2025",
    "viewChange": 181466,
    "viewChange_str": "+181,466",
    "trend": "up",
    "rank": 36,
    "rankChange": -11,
    "rankChange_str": "-11"
  },
  {
    "id": "wX1VtVxfvw4",
    "title": "NUEVA CAJA de BRAWLER GRATIS Y CAMBIO OCULTO en BULL | SNEAK PEEK de BRAWL STARS",
    "channel": "GoDeiK",
    "views": 181172,
    "views_str": "181.2K views",
    "url": "https://www.youtube.com/watch?v=wX1VtVxfvw4",
    "embed_url": "https://www.youtube.com/embed/wX1VtVxfvw4",
    "thumbnail": "https://i.ytimg.com/vi/wX1VtVxfvw4/mqdefault.jpg",
    "published_at": "2025-09-01T15:01:41Z",
    "published_date_formatted": "01.09.2025",
    "viewChange": 181172,
    "viewChange_str": "+181,172",
    "trend": "up",
    "rank": 37,
    "rankChange": 0,
    "rankChange_str": "+0"
  },
  {
    "id": "SKQWT0As7oc",
    "title": "Demon Slayer: Kimetsu no Yaiba Castillo Infinito | TRAILER  EN ESPAÑOL",
    "channel": "Crunchyroll en Español",
    "views": 163289,
    "views_str": "163.3K views",
    "url": "https://www.youtube.com/watch?v=SKQWT0As7oc",
    "embed_url": "https://www.youtube.com/embed/SKQWT0As7oc",
    "thumbnail": "https://i.ytimg.com/vi/SKQWT0As7oc/mqdefault.jpg",
    "published_at": "2025-09-01T16:00:48Z",
    "published_date_formatted": "01.09.2025",
    "viewChange": 163289,
    "viewChange_str": "+163,289",
    "trend": "up",
    "rank": 38,
    "rankChange": -30,
    "rankChange_str": "-30"
  },
  {
    "id": "Aiz0qwdoCXU",
    "title": "HELLDIVERS 2 – Into the Unjust | Launch Trailer",
    "channel": "HELLDIVERS™ 2",
    "views": 158892,
    "views_str": "158.9K views",
    "url": "https://www.youtube.com/watch?v=Aiz0qwdoCXU",
    "embed_url": "https://www.youtube.com/embed/Aiz0qwdoCXU",
    "thumbnail": "https://i.ytimg.com/vi/Aiz0qwdoCXU/mqdefault.jpg",
    "published_at": "2025-09-02T08:59:00Z",
    "published_date_formatted": "02.09.2025",
    "viewChange": 158892,
    "viewChange_str": "+158,892",
    "trend": "up",
    "rank": 39,
    "rankChange": -28,
    "rankChange_str": "-28"
  },
  {
    "id": "G8_uFg6XNEA",
    "title": "Shakira - Soltera (Letra)",
    "channel": "Big Sound",
    "views": 128951,
    "views_str": "129.0K views",
    "url": "https://www.youtube.com/watch?v=G8_uFg6XNEA",
    "embed_url": "https://www.youtube.com/embed/G8_uFg6XNEA",
    "thumbnail": "https://i.ytimg.com/vi/G8_uFg6XNEA/mqdefault.jpg",
    "published_at": "2025-08-28T18:13:24Z",
    "published_date_formatted": "28.08.2025",
    "viewChange": 128951,
    "viewChange_str": "+128,951",
    "trend": "up",
    "rank": 40,
    "rankChange": 0,
    "rankChange_str": "+0"
  },
  {
    "id": "10pCyWhZojQ",
    "title": "Skinny Flex - GRRR POW (Official Video) #spanishdrill",
    "channel": "Skinny Flex",
    "views": 128889,
    "views_str": "128.9K views",
    "url": "https://www.youtube.com/watch?v=10pCyWhZojQ",
    "embed_url": "https://www.youtube.com/embed/10pCyWhZojQ",
    "thumbnail": "https://i.ytimg.com/vi/10pCyWhZojQ/mqdefault.jpg",
    "published_at": "2025-08-28T20:00:06Z",
    "published_date_formatted": "28.08.2025",
    "viewChange": 128889,
    "viewChange_str": "+128,889",
    "trend": "up",
    "rank": 41,
    "rankChange": 3,
    "rankChange_str": "+3"
  },
  {
    "id": "zMgsRl-rMis",
    "title": "TRIPLE 7,Patinete de ORO y MEDICINA NEW en SCHEDULE 1 #9",
    "channel": "VEGETTA777",
    "views": 123337,
    "views_str": "123.3K views",
    "url": "https://www.youtube.com/watch?v=zMgsRl-rMis",
    "embed_url": "https://www.youtube.com/embed/zMgsRl-rMis",
    "thumbnail": "https://i.ytimg.com/vi/zMgsRl-rMis/mqdefault.jpg",
    "published_at": "2025-09-01T18:31:27Z",
    "published_date_formatted": "01.09.2025",
    "viewChange": 123337,
    "viewChange_str": "+123,337",
    "trend": "up",
    "rank": 42,
    "rankChange": -1,
    "rankChange_str": "-1"
  },
  {
    "id": "jR7PdgOEEh4",
    "title": "🔴 CIERRE DE MERCADO DE FICHAJES EN DIRECTO ! DjMaRiiO",
    "channel": "DjMaRiiO",
    "views": 120363,
    "views_str": "120.4K views",
    "url": "https://www.youtube.com/watch?v=jR7PdgOEEh4",
    "embed_url": "https://www.youtube.com/embed/jR7PdgOEEh4",
    "thumbnail": "https://i.ytimg.com/vi/jR7PdgOEEh4/mqdefault.jpg",
    "published_at": "2025-09-01T23:23:56Z",
    "published_date_formatted": "01.09.2025",
    "viewChange": 120363,
    "viewChange_str": "+120,363",
    "trend": "up",
    "rank": 43,
    "rankChange": -10,
    "rankChange_str": "-10"
  },
  {
    "id": "o3Ea1l_lwmI",
    "title": "FOLAGOR vs DEDSAFIO - CAMPEONATO 2",
    "channel": "Folagor03",
    "views": 89503,
    "views_str": "89.5K views",
    "url": "https://www.youtube.com/watch?v=o3Ea1l_lwmI",
    "embed_url": "https://www.youtube.com/embed/o3Ea1l_lwmI",
    "thumbnail": "https://i.ytimg.com/vi/o3Ea1l_lwmI/mqdefault.jpg",
    "published_at": "2025-09-01T22:39:10Z",
    "published_date_formatted": "01.09.2025",
    "viewChange": 89503,
    "viewChange_str": "+89,503",
    "trend": "up",
    "rank": 44,
    "rankChange": -15,
    "rankChange_str": "-15"
  },
  {
    "id": "PBGrqWxUZwQ",
    "title": "SOBREANÁLISIS del TRÁILER de LANZAMIENTO de SILKSONG",
    "channel": "Todo Hollow Knight",
    "views": 72385,
    "views_str": "72.4K views",
    "url": "https://www.youtube.com/watch?v=PBGrqWxUZwQ",
    "embed_url": "https://www.youtube.com/embed/PBGrqWxUZwQ",
    "thumbnail": "https://i.ytimg.com/vi/PBGrqWxUZwQ/mqdefault.jpg",
    "published_at": "2025-08-30T17:43:21Z",
    "published_date_formatted": "30.08.2025",
    "viewChange": 72385,
    "viewChange_str": "+72,385",
    "trend": "up",
    "rank": 45,
    "rankChange": -22,
    "rankChange_str": "-22"
  },
  {
    "id": "aBiR-cEHp8Q",
    "title": "OT 2025: Los elegidos - Tráiler | Prime Video",
    "channel": "Amazon Prime Video España",
    "views": 56832,
    "views_str": "56.8K views",
    "url": "https://www.youtube.com/watch?v=aBiR-cEHp8Q",
    "embed_url": "https://www.youtube.com/embed/aBiR-cEHp8Q",
    "thumbnail": "https://i.ytimg.com/vi/aBiR-cEHp8Q/mqdefault.jpg",
    "published_at": "2025-09-01T10:05:51Z",
    "published_date_formatted": "01.09.2025",
    "viewChange": 56832,
    "viewChange_str": "+56,832",
    "trend": "up",
    "rank": 46,
    "rankChange": -41,
    "rankChange_str": "-41"
  },
  {
    "id": "5sv5kZJlpn4",
    "title": "He probado TODOS LOS COCHES de la esperada 0.3 de Assetto Corsa EVO, una gran decepción",
    "channel": "Billy Cherokee",
    "views": 52702,
    "views_str": "52.7K views",
    "url": "https://www.youtube.com/watch?v=5sv5kZJlpn4",
    "embed_url": "https://www.youtube.com/embed/5sv5kZJlpn4",
    "thumbnail": "https://i.ytimg.com/vi/5sv5kZJlpn4/mqdefault.jpg",
    "published_at": "2025-09-01T19:00:09Z",
    "published_date_formatted": "01.09.2025",
    "viewChange": 52702,
    "viewChange_str": "+52,702",
    "trend": "up",
    "rank": 47,
    "rankChange": -2,
    "rankChange_str": "-2"
  },
  {
    "id": "pWjy4HtKqgc",
    "title": "KAZE - LO MÍO [MARBELLA 3]",
    "channel": "KAZE",
    "views": 48242,
    "views_str": "48.2K views",
    "url": "https://www.youtube.com/watch?v=pWjy4HtKqgc",
    "embed_url": "https://www.youtube.com/embed/pWjy4HtKqgc",
    "thumbnail": "https://i.ytimg.com/vi/pWjy4HtKqgc/mqdefault.jpg",
    "published_at": "2025-08-31T15:32:09Z",
    "published_date_formatted": "31.08.2025",
    "viewChange": 48242,
    "viewChange_str": "+48,242",
    "trend": "up",
    "rank": 48,
    "rankChange": -41,
    "rankChange_str": "-41"
  },
  {
    "id": "EtctW90eyHE",
    "title": "Nanpa Básico & Beéle - Hasta Aquí Llegué (Letra/Lyrics)",
    "channel": "Pulse Latin",
    "views": 45341,
    "views_str": "45.3K views",
    "url": "https://www.youtube.com/watch?v=EtctW90eyHE",
    "embed_url": "https://www.youtube.com/embed/EtctW90eyHE",
    "thumbnail": "https://i.ytimg.com/vi/EtctW90eyHE/mqdefault.jpg",
    "published_at": "2025-08-30T18:00:15Z",
    "published_date_formatted": "30.08.2025",
    "viewChange": 45341,
    "viewChange_str": "+45,341",
    "trend": "up",
    "rank": 49,
    "rankChange": -15,
    "rankChange_str": "-15"
  },
  {
    "id": "30Grh0qDPpo",
    "title": "He cometido el mayor FALLO de mi CARRERA...",
    "channel": "Spursito El Mejor",
    "views": 44573,
    "views_str": "44.6K views",
    "url": "https://www.youtube.com/watch?v=30Grh0qDPpo",
    "embed_url": "https://www.youtube.com/embed/30Grh0qDPpo",
    "thumbnail": "https://i.ytimg.com/vi/30Grh0qDPpo/mqdefault.jpg",
    "published_at": "2025-09-01T12:47:30Z",
    "published_date_formatted": "01.09.2025",
    "viewChange": 44573,
    "viewChange_str": "+44,573",
    "trend": "up",
    "rank": 50,
    "rankChange": -29,
    "rankChange_str": "-29"
  }
]